README.md
setup.cfg
setup.py
ibm_cloud_security_advisor_findingsapi_sdk.egg-info/PKG-INFO
ibm_cloud_security_advisor_findingsapi_sdk.egg-info/SOURCES.txt
ibm_cloud_security_advisor_findingsapi_sdk.egg-info/dependency_links.txt
ibm_cloud_security_advisor_findingsapi_sdk.egg-info/requires.txt
ibm_cloud_security_advisor_findingsapi_sdk.egg-info/top_level.txt
ibm_security_advisor_findings_api_sdk/__init__.py
ibm_security_advisor_findings_api_sdk/common.py
ibm_security_advisor_findings_api_sdk/findings_api_v1.py
ibm_security_advisor_findings_api_sdk/version.py