Metadata-Version: 2.1
Name: ibm-cloud-security-advisor-findingsapi-sdk
Version: 2.0.7
Summary: Findings API Client SDK
Home-page: https://github.com/ibm-cloud-security/security-advisor-findings-sdk-python
Author: IBM Cloud
Author-email: vkalangu@in.ibm.com, skairali@in.ibm.com, ashishth@in.ibm.com
License: Apache 2.0
Keywords: Swagger,Findings API
Platform: UNKNOWN
